{
  "openapi": "3.0.3",
  "info": {
    "title": "IT Top Journal API",
    "version": "2026-04-11",
    "description": "Auto-generated documentation from daily Journal API collection."
  },
  "paths": {
    "/auth/login": {
      "post": {
        "summary": "POST /auth/login",
        "description": "Auto-generated operation for `/auth/login`.",
        "responses": {
          "200": {
            "description": "Successful response",
            "content": {
              "application/json": {
                "schema": {
                  "type": "object",
                  "additionalProperties": true
                }
              }
            }
          }
        },
        "requestBody": {
          "required": true,
          "content": {
            "application/json": {
              "schema": {
                "type": "object",
                "additionalProperties": true
              },
              "example": {
                "application_key": "",
                "id_city": null,
                "login": "<login>",
                "password": "<password>"
              }
            }
          }
        }
      }
    },
    "/settings/user-info": {
      "get": {
        "summary": "GET /settings/user-info",
        "description": "Auto-generated operation for `/settings/user-info`.",
        "responses": {
          "200": {
            "description": "Successful response",
            "content": {
              "application/json": {
                "schema": {
                  "type": "object",
                  "additionalProperties": true
                },
                "example": {
                  "groups": [
                    {
                      "group_status": 70446,
                      "is_primary": true,
                      "id": 61449,
                      "name": "ZYTjjQaHHpu"
                    }
                  ],
                  "manual_link": null,
                  "student_id": 62599,
                  "current_group_id": 88583,
                  "full_name": "AOHxnndpmWuLTqA",
                  "achieves_count": 46784,
                  "stream_id": 89320,
                  "stream_name": "DYPVja",
                  "group_name": "YExxETzrnwRKzxm",
                  "level": 87221,
                  "photo": "http://www.wilson-dawson.com/",
                  "gaming_points": [
                    {
                      "new_gaming_point_types__id": 36715,
                      "points": 31638
                    },
                    {
                      "new_gaming_point_types__id": 38871,
                      "points": 3924
                    }
                  ],
                  "spent_gaming_points": [],
                  "visibility": {
                    "is_design": false,
                    "is_video_courses": false,
                    "is_vacancy": false,
                    "is_signal": true,
                    "is_promo": false,
                    "is_test": false,
                    "is_email_verified": true,
                    "is_quizzes_expired": false,
                    "is_debtor": false,
                    "is_phone_verified": true,
                    "is_only_profile": false,
                    "is_referral_program": false,
                    "is_dz_group_issue": true,
                    "is_birthday": false,
                    "is_school": false,
                    "is_news_popup": false,
                    "is_school_branch": false,
                    "is_college_branch": true,
                    "is_higher_education_branch": false,
                    "is_russian_branch": true,
                    "is_academy_branch": false
                  },
                  "current_group_status": 75016,
                  "birthday": "2026-01-08T14:42:07.910899",
                  "age": 65287,
                  "last_date_visit": "2026-01-07T19:57:28.595853",
                  "registration_date": "2026-02-19T02:05:58.595156",
                  "gender": 71297,
                  "study_form_short_name": "NclUZ"
                }
              }
            }
          }
        }
      }
    },
    "/dashboard/chart/average-progress": {
      "get": {
        "summary": "GET /dashboard/chart/average-progress",
        "description": "Auto-generated operation for `/dashboard/chart/average-progress`.",
        "responses": {
          "200": {
            "description": "Successful response",
            "content": {
              "application/json": {
                "schema": {
                  "type": "object",
                  "additionalProperties": true
                },
                "example": [
                  {
                    "date": "2026-03-17T17:16:32.020960",
                    "points": 30630,
                    "previous_points": null,
                    "has_rasp": null
                  },
                  {
                    "date": "2026-01-06T05:51:55.470299",
                    "points": 35452,
                    "previous_points": 58596,
                    "has_rasp": null
                  },
                  {
                    "date": "2026-03-30T02:24:43.947057",
                    "points": 87335,
                    "previous_points": 11197,
                    "has_rasp": null
                  }
                ]
              }
            }
          }
        }
      }
    },
    "/dashboard/chart/attendance": {
      "get": {
        "summary": "GET /dashboard/chart/attendance",
        "description": "Auto-generated operation for `/dashboard/chart/attendance`.",
        "responses": {
          "200": {
            "description": "Successful response",
            "content": {
              "application/json": {
                "schema": {
                  "type": "object",
                  "additionalProperties": true
                },
                "example": [
                  {
                    "date": "2026-02-27T20:01:06.332274",
                    "points": 91853,
                    "previous_points": null,
                    "has_rasp": true
                  },
                  {
                    "date": "2026-03-31T17:43:28.085792",
                    "points": 43282,
                    "previous_points": 18312,
                    "has_rasp": true
                  },
                  {
                    "date": "2026-03-23T11:39:44.298030",
                    "points": 89622,
                    "previous_points": 37075,
                    "has_rasp": true
                  }
                ]
              }
            }
          }
        }
      }
    },
    "/dashboard/progress/leader-group": {
      "get": {
        "summary": "GET /dashboard/progress/leader-group",
        "description": "Auto-generated operation for `/dashboard/progress/leader-group`.",
        "responses": {
          "200": {
            "description": "Successful response",
            "content": {
              "application/json": {
                "schema": {
                  "type": "object",
                  "additionalProperties": true
                },
                "example": [
                  {
                    "amount": 66554,
                    "id": 59223,
                    "full_name": "rDTmrAtHwKX",
                    "photo_path": "https://mcdaniel-vega.com/",
                    "position": 9303
                  },
                  {
                    "amount": 67713,
                    "id": 62043,
                    "full_name": "UXaThYq",
                    "photo_path": "https://bridges-cohen.com/",
                    "position": 18933
                  },
                  {
                    "amount": 52971,
                    "id": 55855,
                    "full_name": "QYVCVwL",
                    "photo_path": "https://www.mcdaniel.org/",
                    "position": 64551
                  }
                ]
              }
            }
          }
        }
      }
    },
    "/dashboard/progress/leader-stream": {
      "get": {
        "summary": "GET /dashboard/progress/leader-stream",
        "description": "Auto-generated operation for `/dashboard/progress/leader-stream`.",
        "responses": {
          "200": {
            "description": "Successful response",
            "content": {
              "application/json": {
                "schema": {
                  "type": "object",
                  "additionalProperties": true
                },
                "example": [
                  {
                    "id": 90282,
                    "full_name": "eozlVpvtDjwPL",
                    "photo_path": "https://pace.com/",
                    "position": 67074,
                    "amount": 18834
                  },
                  {
                    "id": 67423,
                    "full_name": "JUGJuzZaA",
                    "photo_path": "https://myers-wang.info/",
                    "position": 44334,
                    "amount": 48541
                  },
                  {
                    "id": 36044,
                    "full_name": "YDRAAVeO",
                    "photo_path": "https://mooney-burke.biz/",
                    "position": 50563,
                    "amount": 47016
                  }
                ]
              }
            }
          }
        }
      }
    },
    "/progress/operations/student-visits": {
      "get": {
        "summary": "GET /progress/operations/student-visits",
        "description": "Auto-generated operation for `/progress/operations/student-visits`.",
        "responses": {
          "200": {
            "description": "Successful response",
            "content": {
              "application/json": {
                "schema": {
                  "type": "object",
                  "additionalProperties": true
                },
                "example": [
                  {
                    "date_visit": "2026-02-20T22:49:47.200183",
                    "lesson_number": 46051,
                    "status_was": 9954,
                    "spec_id": 60510,
                    "teacher_name": "lxgMGmQtnIOfOy",
                    "spec_name": "NUNgqfppyvS",
                    "lesson_theme": "sWISYgrfwOei",
                    "control_work_mark": null,
                    "home_work_mark": null,
                    "lab_work_mark": null,
                    "class_work_mark": null,
                    "practical_work_mark": null,
                    "final_work_mark": null
                  },
                  {
                    "date_visit": "2026-01-29T20:55:46.895671",
                    "lesson_number": 49632,
                    "status_was": 46089,
                    "spec_id": 72165,
                    "teacher_name": "omaPPMFmZk",
                    "spec_name": "jRiHSJx",
                    "lesson_theme": "nXNhUT",
                    "control_work_mark": null,
                    "home_work_mark": null,
                    "lab_work_mark": null,
                    "class_work_mark": null,
                    "practical_work_mark": null,
                    "final_work_mark": null
                  },
                  {
                    "date_visit": "2026-03-18T10:30:13.098026",
                    "lesson_number": 99423,
                    "status_was": 8068,
                    "spec_id": 66386,
                    "teacher_name": "ThsXIaAaURNjRKa",
                    "spec_name": "OthbNSqQHWcm",
                    "lesson_theme": "NgYXzkEjFLh",
                    "control_work_mark": null,
                    "home_work_mark": null,
                    "lab_work_mark": null,
                    "class_work_mark": null,
                    "practical_work_mark": null,
                    "final_work_mark": null
                  }
                ]
              }
            }
          }
        }
      }
    },
    "/count/homework": {
      "get": {
        "summary": "GET /count/homework",
        "description": "Auto-generated operation for `/count/homework`.",
        "responses": {
          "200": {
            "description": "Successful response",
            "content": {
              "application/json": {
                "schema": {
                  "type": "object",
                  "additionalProperties": true
                },
                "example": [
                  {
                    "counter_type": 75885,
                    "counter": 48315
                  },
                  {
                    "counter_type": 98150,
                    "counter": 14546
                  },
                  {
                    "counter_type": 28456,
                    "counter": 21307
                  }
                ]
              }
            }
          }
        }
      }
    },
    "/schedule/operations/get-by-date": {
      "get": {
        "summary": "GET /schedule/operations/get-by-date",
        "description": "Auto-generated operation for `/schedule/operations/get-by-date`.",
        "responses": {
          "200": {
            "description": "Successful response",
            "content": {
              "application/json": {
                "schema": {
                  "type": "object",
                  "additionalProperties": true
                },
                "example": []
              }
            }
          }
        },
        "parameters": [
          {
            "name": "date",
            "in": "query",
            "required": false,
            "schema": {
              "type": "string"
            },
            "example": "2026-04-11"
          }
        ]
      }
    },
    "/reviews/index/list": {
      "get": {
        "summary": "GET /reviews/index/list",
        "description": "Auto-generated operation for `/reviews/index/list`.",
        "responses": {
          "200": {
            "description": "Successful response",
            "content": {
              "application/json": {
                "schema": {
                  "type": "object",
                  "additionalProperties": true
                },
                "example": [
                  {
                    "date": "2026-01-03T07:59:59.396359",
                    "message": "xWwZQJuOC",
                    "spec": "nYPQu",
                    "full_spec": "BNimUYBdDElA",
                    "teacher": "VwMEskodcf"
                  },
                  {
                    "date": "2026-02-26T14:19:28.650471",
                    "message": "XsbHZLztx",
                    "spec": "zPWfkQzFFWfgXGf",
                    "full_spec": "vHGAHeuiFH",
                    "teacher": "NTHvgFvygkVhcMb"
                  },
                  {
                    "date": "2026-02-17T23:40:02.001919",
                    "message": "yjQxOmj",
                    "spec": "tJkpEhS",
                    "full_spec": "cUnMNXZLoUp",
                    "teacher": "ktfBkoxwgMC"
                  }
                ]
              }
            }
          }
        }
      }
    },
    "/feedback/students/evaluate-lesson-list": {
      "get": {
        "summary": "GET /feedback/students/evaluate-lesson-list",
        "description": "Auto-generated operation for `/feedback/students/evaluate-lesson-list`.",
        "responses": {
          "200": {
            "description": "Successful response",
            "content": {
              "application/json": {
                "schema": {
                  "type": "object",
                  "additionalProperties": true
                },
                "example": [
                  {
                    "key": "ZdLedi",
                    "date_visit": "2026-03-23T02:54:30.508438",
                    "fio_teach": "iaeoRFsNYJ",
                    "spec_name": "CBIaNAvyEKT",
                    "teach_photo": null
                  },
                  {
                    "key": "LdzlGYmlRTqS",
                    "date_visit": "2026-03-20T00:22:46.580135",
                    "fio_teach": "EfALnIQmsa",
                    "spec_name": "tsMoHlGPyhbbeA",
                    "teach_photo": null
                  },
                  {
                    "key": "yMVuYTtHSWBswHz",
                    "date_visit": "2026-02-01T06:03:39.335664",
                    "fio_teach": "SuZbkvqFFVkpxpE",
                    "spec_name": "VjuFm",
                    "teach_photo": null
                  }
                ]
              }
            }
          }
        }
      }
    },
    "/public/tags": {
      "get": {
        "summary": "GET /public/tags",
        "description": "Auto-generated operation for `/public/tags`.",
        "responses": {
          "200": {
            "description": "Successful response",
            "content": {
              "application/json": {
                "schema": {
                  "type": "object",
                  "additionalProperties": true
                },
                "example": []
              }
            }
          }
        }
      }
    }
  }
}
